README.md
setup.py
pritunlsdk/__init__.py
pritunlsdk/auth.py
pritunlsdk/user.py
pritunlsdk.egg-info/PKG-INFO
pritunlsdk.egg-info/SOURCES.txt
pritunlsdk.egg-info/dependency_links.txt
pritunlsdk.egg-info/not-zip-safe
pritunlsdk.egg-info/requires.txt
pritunlsdk.egg-info/top_level.txt