Metadata-Version: 1.0
Name: pritunlsdk
Version: 0.1
Summary: Unofficial Pritunl SDK written in Python that allows to easily intract with Pritunl API
Home-page: http://github.com/chaordic/pritunl-python-sdk
Author: Raphael P. Ribeiro
Author-email: raphael.ribeiro@chaordicsystems.com
License: GPL
Platform: UNKNOWN
